Metadata-Version: 1.0
Name: ezstats
Version: 1.0
Summary: Gaussian, Binomial, and Uniform distributions
Home-page: UNKNOWN
Author: UNKNOWN
Author-email: UNKNOWN
License: UNKNOWN
Platform: UNKNOWN
